{
  "$schema": "https://raw.githubusercontent.com/microsoft/vcpkg-tool/main/docs/vcpkg.schema.json",
  "builtin-baseline": "5f8c424e267b7360d451df406eeefb3767985b17",
  "dependencies": [
    {
      "name": "tokenizer",
      "version>=": "1.37.1"
    },
    {
      "name": "ctranslate2",
      "version>=": "4.5.0",
      "default-features": false,
      "features": [
        "cpu-dispatch",
        "dnnl"
      ]
    }
  ],
  "homepage": "https://github.com/paoldev/Paoldev.OfflineTextTranslator",
  "license": "MIT",
  "maintainers": "paoldev",
  "supports": "windows & x64",
  "vcpkg-configuration": {
    "overlay-ports": [
      "./vcpkg-custom-overlays/ports"
    ]
  }
}
